LICENSE.txt
README.rst
setup.py
reconnecting_ftp/__init__.py
reconnecting_ftp.egg-info/PKG-INFO
reconnecting_ftp.egg-info/SOURCES.txt
reconnecting_ftp.egg-info/dependency_links.txt
reconnecting_ftp.egg-info/requires.txt
reconnecting_ftp.egg-info/top_level.txt
tests/test_reconnecting_ftp.py