Metadata-Version: 2.1
Name: reconnecting_ftp
Version: 1.1.2
Summary: Reconnecting FTP client
Home-page: https://github.com/Parquery/reconnecting-ftp
Author: Marko Ristin
Author-email: marko@ristin.ch
Keywords: ftplib reconnect retry robust ftp client
Classifier: Development Status :: 5 - Production/Stable
Classifier: Intended Audience :: Developers
Classifier: License :: OSI Approved :: MIT License
Classifier: Programming Language :: Python :: 3.7
Classifier: Programming Language :: Python :: 3.8
Classifier: Programming Language :: Python :: 3.9
Classifier: Programming Language :: Python :: 3.10
Classifier: Programming Language :: Python :: 3.11
License-File: LICENSE.txt
Provides-Extra: test
Requires-Dist: pyftpdlib; extra == "test"
Provides-Extra: dev
Requires-Dist: mypy==1.4.1; extra == "dev"
Requires-Dist: pylint==2.17.7; extra == "dev"
Requires-Dist: yapf==0.40.2; extra == "dev"
Requires-Dist: pyftpdlib; extra == "dev"
Requires-Dist: coverage==7.2.7; extra == "dev"
